yinsolidated/__init__.py
yinsolidated/_common.py
yinsolidated/_version.py
yinsolidated/parser.py
yinsolidated/plugin/__init__.py
yinsolidated/plugin/plugin.py
yinsolidated-1.3.0.dist-info/LICENSE.txt
yinsolidated-1.3.0.dist-info/METADATA
yinsolidated-1.3.0.dist-info/WHEEL
yinsolidated-1.3.0.dist-info/entry_points.txt
yinsolidated-1.3.0.dist-info/top_level.txt
yinsolidated-1.3.0.dist-info/RECORD
