Metadata-Version: 2.1
Name: yinsolidated
Version: 1.3.0
Summary: Generates and parses a YIN-like representation of a YANG model, consolidated into a single XML document
Home-page: https://github.com/128technology/yinsolidated
Author: Alex Thompson
Author-email: alex@128technology.com
License: MIT
Keywords: yang yin pyang
Platform: UNKNOWN
Classifier: Development Status :: 5 - Production/Stable
Classifier: Intended Audience :: Developers
Classifier: License :: OSI Approved :: MIT License
Classifier: Natural Language :: English
Classifier: Programming Language :: Python
Classifier: Programming Language :: Python :: 2
Classifier: Programming Language :: Python :: 2.7
Classifier: Programming Language :: Python :: 3
Classifier: Programming Language :: Python :: 3.4
Classifier: Programming Language :: Python :: 3.5
Classifier: Programming Language :: Python :: 3.6
Classifier: Topic :: Software Development :: Libraries :: Python Modules
Requires-Python: >=2.7
Requires-Dist: lxml (>=3.7.3)
Requires-Dist: xpathparser (>=1.0.0)
